[
  {
    "title": "使用语雀管理博客",
    "description": "Test",
    "created_at": "2018-11-09T12:43:26.000Z",
    "updated_at": "2018-11-09T13:33:32.000Z",
    "published_at": "2018-11-09T13:33:32.000Z",
    "format": "asl",
    "slug": "momb9q",
    "last_editor": {
      "id": 183307,
      "type": "User",
      "login": "leafly",
      "name": "leafly",
      "description": null,
      "avatar_url": "https://gw.alipayobjects.com/zos/rmsportal/wYnHWSXDmBhiEmuwXsym.png",
      "large_avatar_url": "https://gw.alipayobjects.com/zos/rmsportal/wYnHWSXDmBhiEmuwXsym.png?x-oss-process=image/resize,m_fill,w_320,h_320",
      "medium_avatar_url": "https://gw.alipayobjects.com/zos/rmsportal/wYnHWSXDmBhiEmuwXsym.png?x-oss-process=image/resize,m_fill,w_160,h_160",
      "small_avatar_url": "https://gw.alipayobjects.com/zos/rmsportal/wYnHWSXDmBhiEmuwXsym.png?x-oss-process=image/resize,m_fill,w_80,h_80",
      "followers_count": 0,
      "following_count": 0,
      "created_at": "2018-09-27T09:52:55.000Z",
      "updated_at": "2018-11-09T13:31:57.000Z",
      "_serializer": "v2.user"
    },
    "body": "## <a name=\"uxirrk\"></a>Test\n\n"
  }
]